[{"id":21,"key":"SummonerBarrier","name":"Lá Chắn","imagefull":"SummonerBarrier.png","imagelink":"https://ddragon.leagueoflegends.com/cdn/8.1.1/img/spell/SummonerBarrier.png"},{"id":30,"key":"SummonerPoroRecall","name":"Hộ Giá!","imagefull":"SummonerPoroRecall.png","imagelink":"https://ddragon.leagueoflegends.com/cdn/8.1.1/img/spell/SummonerPoroRecall.png"},{"id":39,"key":"SummonerSnowURFSnowball_Mark","name":"Đánh Dấu Siêu Tốc","imagefull":"SummonerSnowURFSnowball_Mark.png","imagelink":"https://ddragon.leagueoflegends.com/cdn/8.1.1/img/spell/SummonerSnowURFSnowball_Mark.png"},{"id":1,"key":"SummonerBoost","name":"Thanh Tẩy","imagefull":"SummonerBoost.png","imagelink":"https://ddragon.leagueoflegends.com/cdn/8.1.1/img/spell/SummonerBoost.png"},{"id":36,"key":"SummonerDarkStarChampSelect2","name":"Tắt Phép Bổ Trợ","imagefull":"SummonerDarkStarChampSelect2.png","imagelink":"https://ddragon.leagueoflegends.com/cdn/8.1.1/img/spell/SummonerDarkStarChampSelect2.png"},{"id":12,"key":"SummonerTeleport","name":"Dịch Chuyển","imagefull":"SummonerTeleport.png","imagelink":"https://ddragon.leagueoflegends.com/cdn/8.1.1/img/spell/SummonerTeleport.png"},{"id":35,"key":"SummonerDarkStarChampSelect1","name":"Tắt Phép Bổ Trợ","imagefull":"SummonerDarkStarChampSelect1.png","imagelink":"https://ddragon.leagueoflegends.com/cdn/8.1.1/img/spell/SummonerDarkStarChampSelect1.png"},{"id":4,"key":"SummonerFlash","name":"Tốc Biến","imagefull":"SummonerFlash.png","imagelink":"https://ddragon.leagueoflegends.com/cdn/8.1.1/img/spell/SummonerFlash.png"},{"id":32,"key":"SummonerSnowball","name":"Đánh Dấu","imagefull":"SummonerSnowball.png","imagelink":"https://ddragon.leagueoflegends.com/cdn/8.1.1/img/spell/SummonerSnowball.png"},{"id":7,"key":"SummonerHeal","name":"Hồi Máu","imagefull":"SummonerHeal.png","imagelink":"https://ddragon.leagueoflegends.com/cdn/8.1.1/img/spell/SummonerHeal.png"},{"id":13,"key":"SummonerMana","name":"Minh Mẫn","imagefull":"SummonerMana.png","imagelink":"https://ddragon.leagueoflegends.com/cdn/8.1.1/img/spell/SummonerMana.png"},{"id":31,"key":"SummonerPoroThrow","name":"Ném Poro","imagefull":"SummonerPoroThrow.png","imagelink":"https://ddragon.leagueoflegends.com/cdn/8.1.1/img/spell/SummonerPoroThrow.png"},{"id":-1,"key":"SummonerSnowURFSnowball_Mark_FollowupCast","name":"Lướt Tới Siêu Tốc","imagefull":"SummonerSnowURFSnowball_Mark_FollowupCast.png","imagelink":"https://ddragon.leagueoflegends.com/cdn/8.1.1/img/spell/SummonerSnowURFSnowball_Mark_FollowupCast.png"},{"id":11,"key":"SummonerSmite","name":"Trừng Phạt","imagefull":"SummonerSmite.png","imagelink":"https://ddragon.leagueoflegends.com/cdn/8.1.1/img/spell/SummonerSmite.png"},{"id":33,"key":"SummonerSiegeChampSelect1","name":"Nhà Chính Thất Thủ: Khí Cụ","imagefull":"SummonerSiegeChampSelect1.png","imagelink":"https://ddragon.leagueoflegends.com/cdn/8.1.1/img/spell/SummonerSiegeChampSelect1.png"},{"id":34,"key":"SummonerSiegeChampSelect2","name":"Nhà Chính Thất Thủ: Khí Cụ","imagefull":"SummonerSiegeChampSelect2.png","imagelink":"https://ddragon.leagueoflegends.com/cdn/8.1.1/img/spell/SummonerSiegeChampSelect2.png"},{"id":3,"key":"SummonerExhaust","name":"Kiệt Sức","imagefull":"SummonerExhaust.png","imagelink":"https://ddragon.leagueoflegends.com/cdn/8.1.1/img/spell/SummonerExhaust.png"},{"id":14,"key":"SummonerDot","name":"Thiêu Đốt","imagefull":"SummonerDot.png","imagelink":"https://ddragon.leagueoflegends.com/cdn/8.1.1/img/spell/SummonerDot.png"},{"id":6,"key":"SummonerHaste","name":"Tốc Hành","imagefull":"SummonerHaste.png","imagelink":"https://ddragon.leagueoflegends.com/cdn/8.1.1/img/spell/SummonerHaste.png"}]